tgedr/pipeline/common/__init__.py
tgedr/pipeline/common/common.py
tgedr/pipeline/common/factory.py
tgedr/pipeline/common/sink.py
tgedr/pipeline/common/source.py
tgedr/pipeline/common/impl/__init__.py
tgedr/pipeline/common/impl/dummy.py
tgedr_pipeline_common-0.1.10.dist-info/LICENSE
tgedr_pipeline_common-0.1.10.dist-info/METADATA
tgedr_pipeline_common-0.1.10.dist-info/WHEEL
tgedr_pipeline_common-0.1.10.dist-info/top_level.txt
tgedr_pipeline_common-0.1.10.dist-info/RECORD
