Metadata-Version: 2.1
Name: tgedr-pipeline-common
Version: 0.1.10
Summary: This package provides interfaces to the pipeline set of packages
Home-page: https://github.com/tgedr/pipeline-common
Author: joao tiago viegas
Author-email: jtviegas.js@gmail.com
License: Unlicense
Platform: UNKNOWN
Classifier: Programming Language :: Python :: 3
Classifier: Programming Language :: Python :: 3.7
License-File: LICENSE
Requires-Dist: configlookup
Requires-Dist: pytest
